Metadata-Version: 2.1
Name: grants-tagger
Version: 0.2.5
Summary: A machine learning model to tag grants
Author: Arne Robben
Author-email: a.robben@wellcome.ac.uk
License-File: LICENSE
Requires-Dist: scikit-learn (==1.0.0)
Requires-Dist: libpecos (==0.3.0)
Requires-Dist: typer
Requires-Dist: pandas
Requires-Dist: numpy
Requires-Dist: scipy
Requires-Dist: requests
Requires-Dist: dvc
Requires-Dist: wasabi
Requires-Dist: wellcomeml
Requires-Dist: gensim (==4.0.0)
